tests/booktest.py
hantibookmanager-0.1.3.dist-info/METADATA
hantibookmanager-0.1.3.dist-info/WHEEL
hantibookmanager-0.1.3.dist-info/top_level.txt
hantibookmanager-0.1.3.dist-info/RECORD
