Metadata-Version: 2.4
Name: hantibookmanager
Version: 0.1.3
Summary: A simple book management system
Author: hanti
Author-email: hanti <hanti.hgt@gmail.com>
License: MIT
Classifier: Programming Language :: Python :: 3
Classifier: Operating System :: OS Independent
Requires-Python: >=3.8
